Metadata-Version: 2.1
Name: light-embed-awslambda
Version: 1.0.0
Summary: Fast and Lightweight Text Embedding
Author: Binh Nguyen
Requires-Python: <=3.13,>=3.9
Requires-Dist: python-dotenv==1.0.1
Requires-Dist: numpy==1.26.4
Requires-Dist: huggingface-hub==0.25.2
Requires-Dist: onnxruntime==1.19.0
Requires-Dist: tokenizers==0.20.0
Provides-Extra: dev
Requires-Dist: pytest==8.2.1; extra == "dev"
Requires-Dist: pytest-cov==5.0.0; extra == "dev"
Requires-Dist: tox==4.15.1; extra == "dev"
Requires-Dist: black==24.4.2; extra == "dev"
Requires-Dist: pip-tools==7.4.1; extra == "dev"
Requires-Dist: flake8==7.1.0; extra == "dev"
